polysynth/.DS_Store
polysynth/__init__.py
polysynth/abi.py
polysynth/address.py
polysynth/assets/.DS_Store
polysynth/assets/AggregatorV3InterfaceABI.json
polysynth/assets/local.json
polysynth/assets/matic.json
polysynth/assets/mumbai.json
polysynth/constants.py
polysynth/enum.py
polysynth/exception.py
polysynth/polysynth.py
polysynth/types.py
polysynth/util.py
polysynth-0.7.2.dist-info/entry_points.txt
polysynth-0.7.2.dist-info/WHEEL
polysynth-0.7.2.dist-info/METADATA
polysynth-0.7.2.dist-info/RECORD
