Metadata-Version: 2.1
Name: polysynth
Version: 0.7.2
Summary: Official Python wrapper for the Polysynth platform
Home-page: https://github.com/kryptolabs/polysynth-python
License: MIT
Keywords: polysynth,ethereum,polygon,trading
Author: Polysynth
Author-email: bugs@polysynth.com
Requires-Python: >=3.7.2,<4.0.0
Classifier: Intended Audience :: Developers
Classifier: License :: OSI Approved :: MIT License
Classifier: Programming Language :: Python :: 3
Classifier: Programming Language :: Python :: 3.10
Classifier: Programming Language :: Python :: 3.8
Classifier: Programming Language :: Python :: 3.9
Classifier: Topic :: Software Development :: Libraries :: Python Modules
Requires-Dist: beartype (>=0.8.0,<0.9.0)
Requires-Dist: pickleDB (>=0.9.2,<0.10.0)
Requires-Dist: web3 (>=5.24.0,<6.0.0)
Project-URL: Repository, https://github.com/kryptolabs/polysynth-python
